linlearn/__init__.py
linlearn/learner.py
linlearn/loss.py
linlearn/penalty.py
linlearn/simulation.py
linlearn/solver.py
linlearn/strategy.py
linlearn-0.1.dist-info/LICENSE
linlearn-0.1.dist-info/WHEEL
linlearn-0.1.dist-info/METADATA
linlearn-0.1.dist-info/RECORD
