Metadata-Version: 2.1
Name: linlearn
Version: 0.1
Summary: linlear is a python package for machine learning with linear methods, including robust methods
Home-page: https://linlearn.readthedocs.io
Keywords: python,machine-learning,classification,regression,linear-methods,robust-methods
Author: Stéphane Gaïffas
Author-email: stephane.gaiffas@gmail.com
Requires-Python: >=3.6,<4.0
Classifier: Development Status :: 3 - Alpha
Classifier: Intended Audience :: Developers
Classifier: Intended Audience :: Science/Research
Classifier: License :: OSI Approved :: BSD License
Classifier: Operating System :: POSIX
Classifier: Operating System :: Unix
Classifier: Programming Language :: Python
Classifier: Programming Language :: Python :: 3
Classifier: Programming Language :: Python :: 3.6
Classifier: Programming Language :: Python :: 3.7
Classifier: Programming Language :: Python :: 3.8
Classifier: Topic :: Software Development :: Libraries :: Python Modules
Requires-Dist: matplotlib (>=3.1,<4.0)
Requires-Dist: numba (>=0.48,<0.49)
Requires-Dist: numpy (>=1.17.4,<2.0.0)
Requires-Dist: scikit-learn (>=0.22,<0.23)
Requires-Dist: scipy (>=1.3.2,<2.0.0)
Requires-Dist: tqdm (>=4.36,<5.0)
Project-URL: Documentation, https://linlearn.readthedocs.io
Project-URL: Repository, https://github.com/linlearn/linlearn
